{
  "$schema": "https://developer.microsoft.com/json-schemas/fabric/item/report/definition/visualContainer/2.5.0/schema.json",
  "name": "b84d5fe60a9780e6e22c",
  "position": {
    "x": 693.72262773722628,
    "y": 456.35036496350369,
    "z": 9000,
    "height": 239.12408759124088,
    "width": 263.64963503649636,
    "tabOrder": 9000
  },
  "visual": {
    "visualType": "donutChart",
    "query": {
      "queryState": {
        "Category": {
          "projections": [
            {
              "field": {
                "Column": {
                  "Expression": {
                    "SourceRef": {
                      "Entity": "DatasetRH"
                    }
                  },
                  "Property": "Envolvimento_Trabalho"
                }
              },
              "queryRef": "DatasetRH.Envolvimento_Trabalho",
              "nativeQueryRef": "Envolvimento_Trabalho",
              "active": true
            }
          ]
        },
        "Y": {
          "projections": [
            {
              "field": {
                "Measure": {
                  "Expression": {
                    "SourceRef": {
                      "Entity": "Medidas"
                    }
                  },
                  "Property": "TotalFunc"
                }
              },
              "queryRef": "Medidas.TotalFunc",
              "nativeQueryRef": "TotalFunc"
            }
          ]
        }
      },
      "sortDefinition": {
        "sort": [
          {
            "field": {
              "Measure": {
                "Expression": {
                  "SourceRef": {
                    "Entity": "Medidas"
                  }
                },
                "Property": "TotalFunc"
              }
            },
            "direction": "Descending"
          }
        ],
        "isDefaultSort": true
      }
    },
    "objects": {
      "legend": [
        {
          "properties": {
            "position": {
              "expr": {
                "Literal": {
                  "Value": "'BottomCenter'"
                }
              }
            },
            "showTitle": {
              "expr": {
                "Literal": {
                  "Value": "false"
                }
              }
            }
          }
        }
      ],
      "labels": [
        {
          "properties": {
            "labelStyle": {
              "expr": {
                "Literal": {
                  "Value": "'Category, percent of total'"
                }
              }
            }
          }
        }
      ]
    },
    "visualContainerObjects": {
      "title": [
        {
          "properties": {
            "bold": {
              "expr": {
                "Literal": {
                  "Value": "true"
                }
              }
            },
            "alignment": {
              "expr": {
                "Literal": {
                  "Value": "'center'"
                }
              }
            },
            "text": {
              "expr": {
                "Literal": {
                  "Value": "'Envolvimento no Trabalho'"
                }
              }
            }
          }
        }
      ]
    },
    "drillFilterOtherVisuals": true
  }
}