{
  "version": "1.1.0",
  "diagrams": [
    {
      "ordinal": 0,
      "scrollPosition": {
        "x": 0,
        "y": 0
      },
      "nodes": [
        {
          "location": {
            "x": 0,
            "y": 0
          },
          "nodeIndex": "DadosFinanceiros",
          "nodeLineageTag": "8318e72e-1aa4-4b21-ab91-130440604c5b",
          "size": {
            "height": 300,
            "width": 234
          },
          "zIndex": 0
        },
        {
          "location": {
            "x": 284,
            "y": 98
          },
          "nodeIndex": "MedidasIndicadoresFinanceiros",
          "nodeLineageTag": "55dded5d-ac9e-4925-8d40-79d450ba942b",
          "size": {
            "height": 337,
            "width": 234
          },
          "zIndex": 0
        }
      ],
      "name": "Todas as tabelas",
      "zoomValue": 100,
      "pinKeyFieldsToTop": false,
      "showExtraHeaderInfo": false,
      "hideKeyFieldsWhenCollapsed": false,
      "tablesLocked": false
    }
  ],
  "selectedDiagram": "Todas as tabelas",
  "defaultDiagram": "Todas as tabelas"
}